{
  "nodes": [
    {
      "id": "ex-finite-field",
      "uri": "https://mathwiki.org/resource/ex-finite-field",
      "label": "Example: Finite Field",
      "type": "Example",
      "index": 0,
      "is_focus": false
    },
    {
      "id": "def-quotient-group",
      "uri": "https://mathwiki.org/resource/def-quotient-group",
      "label": "Definition: Quotient Group",
      "type": "Definition",
      "index": 1,
      "is_focus": false
    },
    {
      "id": "def-identity-element",
      "uri": "https://mathwiki.org/resource/def-identity-element",
      "label": "Definition: Identity Element",
      "type": "Definition",
      "index": 2,
      "is_focus": false
    },
    {
      "id": "def-group-action",
      "uri": "https://mathwiki.org/resource/def-group-action",
      "label": "Group Action",
      "type": "Definition",
      "index": 3,
      "is_focus": false
    },
    {
      "id": "def-continuity",
      "uri": "https://mathwiki.org/resource/def-continuity",
      "label": "Definition: Continuity",
      "type": "Definition",
      "index": 4,
      "is_focus": false
    },
    {
      "id": "def-direct-product",
      "uri": "https://mathwiki.org/resource/def-direct-product",
      "label": "Definition: Direct Product of Groups",
      "type": "Definition",
      "index": 5,
      "is_focus": false
    },
    {
      "id": "def-function",
      "uri": "https://mathwiki.org/resource/def-function",
      "label": "Definition: Function",
      "type": "Definition",
      "index": 6,
      "is_focus": false
    },
    {
      "id": "thm-lagrange",
      "uri": "https://mathwiki.org/resource/thm-lagrange",
      "label": "Theorem: Lagrange's Theorem",
      "type": "Theorem",
      "index": 7,
      "is_focus": false
    },
    {
      "id": "def-inverse-element",
      "uri": "https://mathwiki.org/resource/def-inverse-element",
      "label": "Definition: Inverse Element",
      "type": "Definition",
      "index": 8,
      "is_focus": false
    },
    {
      "id": "def-commutativity",
      "uri": "https://mathwiki.org/resource/def-commutativity",
      "label": "Definition: Commutativity",
      "type": "Definition",
      "index": 9,
      "is_focus": false
    },
    {
      "id": "def-coset",
      "uri": "https://mathwiki.org/resource/def-coset",
      "label": "Definition: Coset",
      "type": "Definition",
      "index": 10,
      "is_focus": false
    },
    {
      "id": "def-polynomial-ring",
      "uri": "https://mathwiki.org/resource/def-polynomial-ring",
      "label": "Definition: Polynomial Ring",
      "type": "Definition",
      "index": 11,
      "is_focus": false
    },
    {
      "id": "def-cyclic-group",
      "uri": "https://mathwiki.org/resource/def-cyclic-group",
      "label": "Definition: Cyclic Group",
      "type": "Definition",
      "index": 12,
      "is_focus": false
    },
    {
      "id": "thm-sylow",
      "uri": "https://mathwiki.org/resource/thm-sylow",
      "label": "Sylow Theorems",
      "type": "Theorem",
      "index": 13,
      "is_focus": false
    },
    {
      "id": "thm-euler",
      "uri": "https://mathwiki.org/resource/thm-euler",
      "label": "Theorem: Euler's Theorem",
      "type": "Theorem",
      "index": 14,
      "is_focus": false
    },
    {
      "id": "def-ring",
      "uri": "https://mathwiki.org/resource/def-ring",
      "label": "Definition: Ring",
      "type": "Definition",
      "index": 15,
      "is_focus": false
    },
    {
      "id": "ex-exponential-homomorphism",
      "uri": "https://mathwiki.org/resource/ex-exponential-homomorphism",
      "label": "Example: Exponential Homomorphism",
      "type": "Example",
      "index": 16,
      "is_focus": false
    },
    {
      "id": "def-random-variable",
      "uri": "https://mathwiki.org/resource/def-random-variable",
      "label": "Definition: Random Variable",
      "type": "Definition",
      "index": 17,
      "is_focus": false
    },
    {
      "id": "ex-integers-ring",
      "uri": "https://mathwiki.org/resource/ex-integers-ring",
      "label": "Example: Integers Form a Ring",
      "type": "Example",
      "index": 18,
      "is_focus": false
    },
    {
      "id": "def-sequence",
      "uri": "https://mathwiki.org/resource/def-sequence",
      "label": "Definition: Sequence",
      "type": "Definition",
      "index": 19,
      "is_focus": false
    },
    {
      "id": "def-metric-space",
      "uri": "https://mathwiki.org/resource/def-metric-space",
      "label": "Definition: Metric Space",
      "type": "Definition",
      "index": 20,
      "is_focus": false
    },
    {
      "id": "def-binary-operation",
      "uri": "https://mathwiki.org/resource/def-binary-operation",
      "label": "Definition: Binary Operation",
      "type": "Definition",
      "index": 21,
      "is_focus": false
    },
    {
      "id": "thm-first-isomorphism",
      "uri": "https://mathwiki.org/resource/thm-first-isomorphism",
      "label": "Theorem: First Isomorphism Theorem",
      "type": "Theorem",
      "index": 22,
      "is_focus": false
    },
    {
      "id": "def-linear-transformation",
      "uri": "https://mathwiki.org/resource/def-linear-transformation",
      "label": "Definition: Linear Transformation",
      "type": "Definition",
      "index": 23,
      "is_focus": false
    },
    {
      "id": "def-abelian-group",
      "uri": "https://mathwiki.org/resource/def-abelian-group",
      "label": "Definition: Abelian Group",
      "type": "Definition",
      "index": 24,
      "is_focus": false
    },
    {
      "id": "def-module",
      "uri": "https://mathwiki.org/resource/def-module",
      "label": "Definition: Module",
      "type": "Definition",
      "index": 25,
      "is_focus": false
    },
    {
      "id": "thm-unique-identity",
      "uri": "https://mathwiki.org/resource/thm-unique-identity",
      "label": "Theorem: Uniqueness of Identity",
      "type": "Theorem",
      "index": 26,
      "is_focus": false
    },
    {
      "id": "ex-group-action-examples",
      "uri": "https://mathwiki.org/resource/ex-group-action-examples",
      "label": "Examples of Group Actions",
      "type": "Example",
      "index": 27,
      "is_focus": false
    },
    {
      "id": "def-subgroup",
      "uri": "https://mathwiki.org/resource/def-subgroup",
      "label": "Definition: Subgroup",
      "type": "Definition",
      "index": 28,
      "is_focus": false
    },
    {
      "id": "def-image",
      "uri": "https://mathwiki.org/resource/def-image",
      "label": "Definition: Image",
      "type": "Definition",
      "index": 29,
      "is_focus": false
    },
    {
      "id": "def-determinant",
      "uri": "https://mathwiki.org/resource/def-determinant",
      "label": "Definition: Determinant",
      "type": "Definition",
      "index": 30,
      "is_focus": false
    },
    {
      "id": "thm-rank-nullity",
      "uri": "https://mathwiki.org/resource/thm-rank-nullity",
      "label": "Theorem: Rank-Nullity Theorem",
      "type": "Theorem",
      "index": 31,
      "is_focus": false
    },
    {
      "id": "def-homeomorphism",
      "uri": "https://mathwiki.org/resource/def-homeomorphism",
      "label": "Definition: Homeomorphism",
      "type": "Definition",
      "index": 32,
      "is_focus": false
    },
    {
      "id": "def-set",
      "uri": "https://mathwiki.org/resource/def-set",
      "label": "Definition: Set",
      "type": "Definition",
      "index": 33,
      "is_focus": false
    },
    {
      "id": "def-associativity",
      "uri": "https://mathwiki.org/resource/def-associativity",
      "label": "Definition: Associativity",
      "type": "Definition",
      "index": 34,
      "is_focus": false
    },
    {
      "id": "def-functor",
      "uri": "https://mathwiki.org/resource/def-functor",
      "label": "Definition: Functor",
      "type": "Definition",
      "index": 35,
      "is_focus": false
    },
    {
      "id": "def-group",
      "uri": "https://mathwiki.org/resource/def-group",
      "label": "Definition: Group",
      "type": "Definition",
      "index": 36,
      "is_focus": false
    },
    {
      "id": "def-field",
      "uri": "https://mathwiki.org/resource/def-field",
      "label": "Definition: Field",
      "type": "Definition",
      "index": 37,
      "is_focus": false
    },
    {
      "id": "ex-quotient-integers-mod-n",
      "uri": "https://mathwiki.org/resource/ex-quotient-integers-mod-n",
      "label": "Example: Integers Modulo n",
      "type": "Example",
      "index": 38,
      "is_focus": false
    },
    {
      "id": "def-normal-subgroup",
      "uri": "https://mathwiki.org/resource/def-normal-subgroup",
      "label": "Definition: Normal Subgroup",
      "type": "Definition",
      "index": 39,
      "is_focus": false
    },
    {
      "id": "def-distributivity",
      "uri": "https://mathwiki.org/resource/def-distributivity",
      "label": "Definition: Distributivity",
      "type": "Definition",
      "index": 40,
      "is_focus": false
    },
    {
      "id": "def-permutation",
      "uri": "https://mathwiki.org/resource/def-permutation",
      "label": "Definition: Permutation",
      "type": "Definition",
      "index": 41,
      "is_focus": false
    },
    {
      "id": "ex-integers-addition",
      "uri": "https://mathwiki.org/resource/ex-integers-addition",
      "label": "Example: Integers under Addition",
      "type": "Example",
      "index": 42,
      "is_focus": false
    },
    {
      "id": "def-vector-space",
      "uri": "https://mathwiki.org/resource/def-vector-space",
      "label": "Definition: Vector Space",
      "type": "Definition",
      "index": 43,
      "is_focus": false
    },
    {
      "id": "def-kernel",
      "uri": "https://mathwiki.org/resource/def-kernel",
      "label": "Definition: Kernel",
      "type": "Definition",
      "index": 44,
      "is_focus": false
    },
    {
      "id": "def-homomorphism",
      "uri": "https://mathwiki.org/resource/def-homomorphism",
      "label": "Definition: Group Homomorphism",
      "type": "Definition",
      "index": 45,
      "is_focus": true
    },
    {
      "id": "def-matrix",
      "uri": "https://mathwiki.org/resource/def-matrix",
      "label": "Definition: Matrix",
      "type": "Definition",
      "index": 46,
      "is_focus": false
    },
    {
      "id": "def-ideal",
      "uri": "https://mathwiki.org/resource/def-ideal",
      "label": "Definition: Ideal",
      "type": "Definition",
      "index": 47,
      "is_focus": false
    },
    {
      "id": "thm-pigeonhole-principle",
      "uri": "https://mathwiki.org/resource/thm-pigeonhole-principle",
      "label": "Theorem: Pigeonhole Principle",
      "type": "Theorem",
      "index": 48,
      "is_focus": false
    },
    {
      "id": "ex-even-integers-subgroup",
      "uri": "https://mathwiki.org/resource/ex-even-integers-subgroup",
      "label": "Example: Even Integers Form a Subgroup",
      "type": "Example",
      "index": 49,
      "is_focus": false
    }
  ],
  "links": [
    {
      "source": 36,
      "target": 1,
      "type": "uses"
    },
    {
      "source": 22,
      "target": 1,
      "type": "uses"
    },
    {
      "source": 25,
      "target": 21,
      "type": "uses"
    },
    {
      "source": 31,
      "target": 44,
      "type": "uses"
    },
    {
      "source": 44,
      "target": 45,
      "type": "uses"
    },
    {
      "source": 1,
      "target": 39,
      "type": "uses"
    },
    {
      "source": 24,
      "target": 1,
      "type": "uses"
    },
    {
      "source": 24,
      "target": 36,
      "type": "uses"
    },
    {
      "source": 39,
      "target": 45,
      "type": "uses"
    },
    {
      "source": 36,
      "target": 21,
      "type": "uses"
    },
    {
      "source": 1,
      "target": 10,
      "type": "uses"
    },
    {
      "source": 39,
      "target": 10,
      "type": "uses"
    },
    {
      "source": 17,
      "target": 6,
      "type": "uses"
    },
    {
      "source": 7,
      "target": 1,
      "type": "uses"
    },
    {
      "source": 1,
      "target": 24,
      "type": "uses"
    },
    {
      "source": 39,
      "target": 24,
      "type": "uses"
    },
    {
      "source": 44,
      "target": 22,
      "type": "uses"
    },
    {
      "source": 15,
      "target": 21,
      "type": "uses"
    },
    {
      "source": 39,
      "target": 30,
      "type": "uses"
    },
    {
      "source": 8,
      "target": 21,
      "type": "uses"
    },
    {
      "source": 21,
      "target": 6,
      "type": "uses"
    },
    {
      "source": 49,
      "target": 39,
      "type": "uses"
    },
    {
      "source": 1,
      "target": 22,
      "type": "uses"
    },
    {
      "source": 39,
      "target": 22,
      "type": "uses"
    },
    {
      "source": 44,
      "target": 23,
      "type": "uses"
    },
    {
      "source": 36,
      "target": 9,
      "type": "uses"
    },
    {
      "source": 34,
      "target": 21,
      "type": "uses"
    },
    {
      "source": 14,
      "target": 1,
      "type": "uses"
    },
    {
      "source": 38,
      "target": 1,
      "type": "uses"
    },
    {
      "source": 42,
      "target": 21,
      "type": "uses"
    },
    {
      "source": 38,
      "target": 36,
      "type": "uses"
    },
    {
      "source": 36,
      "target": 8,
      "type": "uses"
    },
    {
      "source": 44,
      "target": 39,
      "type": "uses"
    },
    {
      "source": 22,
      "target": 36,
      "type": "uses"
    },
    {
      "source": 4,
      "target": 6,
      "type": "uses"
    },
    {
      "source": 41,
      "target": 6,
      "type": "uses"
    },
    {
      "source": 12,
      "target": 5,
      "type": "uses"
    },
    {
      "source": 21,
      "target": 33,
      "type": "uses"
    },
    {
      "source": 3,
      "target": 36,
      "type": "uses"
    },
    {
      "source": 11,
      "target": 21,
      "type": "uses"
    },
    {
      "source": 24,
      "target": 22,
      "type": "uses"
    },
    {
      "source": 36,
      "target": 42,
      "type": "uses"
    },
    {
      "source": 10,
      "target": 1,
      "type": "uses"
    },
    {
      "source": 36,
      "target": 12,
      "type": "uses"
    },
    {
      "source": 32,
      "target": 6,
      "type": "uses"
    },
    {
      "source": 15,
      "target": 36,
      "type": "uses"
    },
    {
      "source": 43,
      "target": 21,
      "type": "uses"
    },
    {
      "source": 36,
      "target": 26,
      "type": "uses"
    },
    {
      "source": 40,
      "target": 21,
      "type": "uses"
    },
    {
      "source": 36,
      "target": 45,
      "type": "uses"
    },
    {
      "source": 22,
      "target": 45,
      "type": "uses"
    },
    {
      "source": 24,
      "target": 39,
      "type": "uses"
    },
    {
      "source": 42,
      "target": 36,
      "type": "uses"
    },
    {
      "source": 10,
      "target": 21,
      "type": "uses"
    },
    {
      "source": 26,
      "target": 36,
      "type": "uses"
    },
    {
      "source": 7,
      "target": 36,
      "type": "uses"
    },
    {
      "source": 28,
      "target": 1,
      "type": "uses"
    },
    {
      "source": 3,
      "target": 6,
      "type": "uses"
    },
    {
      "source": 1,
      "target": 28,
      "type": "uses"
    },
    {
      "source": 39,
      "target": 28,
      "type": "uses"
    },
    {
      "source": 45,
      "target": 21,
      "type": "uses"
    },
    {
      "source": 14,
      "target": 36,
      "type": "uses"
    },
    {
      "source": 36,
      "target": 24,
      "type": "uses"
    },
    {
      "source": 22,
      "target": 24,
      "type": "uses"
    },
    {
      "source": 39,
      "target": 46,
      "type": "uses"
    },
    {
      "source": 6,
      "target": 33,
      "type": "uses"
    },
    {
      "source": 36,
      "target": 33,
      "type": "uses"
    },
    {
      "source": 5,
      "target": 36,
      "type": "uses"
    },
    {
      "source": 43,
      "target": 36,
      "type": "uses"
    },
    {
      "source": 44,
      "target": 43,
      "type": "uses"
    },
    {
      "source": 30,
      "target": 6,
      "type": "uses"
    },
    {
      "source": 19,
      "target": 6,
      "type": "uses"
    },
    {
      "source": 0,
      "target": 1,
      "type": "uses"
    },
    {
      "source": 38,
      "target": 39,
      "type": "uses"
    },
    {
      "source": 24,
      "target": 5,
      "type": "uses"
    },
    {
      "source": 36,
      "target": 2,
      "type": "uses"
    },
    {
      "source": 36,
      "target": 39,
      "type": "uses"
    },
    {
      "source": 10,
      "target": 36,
      "type": "uses"
    },
    {
      "source": 22,
      "target": 39,
      "type": "uses"
    },
    {
      "source": 39,
      "target": 3,
      "type": "uses"
    },
    {
      "source": 16,
      "target": 36,
      "type": "uses"
    },
    {
      "source": 39,
      "target": 7,
      "type": "uses"
    },
    {
      "source": 39,
      "target": 1,
      "type": "uses"
    },
    {
      "source": 5,
      "target": 12,
      "type": "uses"
    },
    {
      "source": 20,
      "target": 6,
      "type": "uses"
    },
    {
      "source": 44,
      "target": 47,
      "type": "uses"
    },
    {
      "source": 27,
      "target": 36,
      "type": "uses"
    },
    {
      "source": 45,
      "target": 1,
      "type": "uses"
    },
    {
      "source": 45,
      "target": 36,
      "type": "uses"
    },
    {
      "source": 5,
      "target": 45,
      "type": "uses"
    },
    {
      "source": 18,
      "target": 21,
      "type": "uses"
    },
    {
      "source": 1,
      "target": 47,
      "type": "uses"
    },
    {
      "source": 23,
      "target": 6,
      "type": "uses"
    },
    {
      "source": 13,
      "target": 36,
      "type": "uses"
    },
    {
      "source": 28,
      "target": 36,
      "type": "uses"
    },
    {
      "source": 10,
      "target": 39,
      "type": "uses"
    },
    {
      "source": 36,
      "target": 0,
      "type": "uses"
    },
    {
      "source": 47,
      "target": 21,
      "type": "uses"
    },
    {
      "source": 12,
      "target": 36,
      "type": "uses"
    },
    {
      "source": 36,
      "target": 34,
      "type": "uses"
    },
    {
      "source": 1,
      "target": 12,
      "type": "uses"
    },
    {
      "source": 16,
      "target": 45,
      "type": "uses"
    },
    {
      "source": 9,
      "target": 21,
      "type": "uses"
    },
    {
      "source": 5,
      "target": 24,
      "type": "uses"
    },
    {
      "source": 22,
      "target": 44,
      "type": "uses"
    },
    {
      "source": 38,
      "target": 5,
      "type": "uses"
    },
    {
      "source": 36,
      "target": 49,
      "type": "uses"
    },
    {
      "source": 36,
      "target": 28,
      "type": "uses"
    },
    {
      "source": 28,
      "target": 39,
      "type": "uses"
    },
    {
      "source": 2,
      "target": 21,
      "type": "uses"
    },
    {
      "source": 45,
      "target": 6,
      "type": "uses"
    },
    {
      "source": 5,
      "target": 33,
      "type": "uses"
    },
    {
      "source": 49,
      "target": 36,
      "type": "uses"
    },
    {
      "source": 22,
      "target": 29,
      "type": "uses"
    },
    {
      "source": 48,
      "target": 6,
      "type": "uses"
    },
    {
      "source": 18,
      "target": 36,
      "type": "uses"
    },
    {
      "source": 44,
      "target": 1,
      "type": "uses"
    },
    {
      "source": 37,
      "target": 36,
      "type": "uses"
    },
    {
      "source": 5,
      "target": 39,
      "type": "uses"
    },
    {
      "source": 1,
      "target": 36,
      "type": "uses"
    },
    {
      "source": 39,
      "target": 36,
      "type": "uses"
    },
    {
      "source": 35,
      "target": 6,
      "type": "uses"
    },
    {
      "source": 45,
      "target": 22,
      "type": "uses"
    }
  ],
  "focus_node": "def-homomorphism",
  "metadata": {
    "total_nodes": 50,
    "total_links": 123,
    "depth": 2
  }
}